smart/__init__.py
smart/common.py
smart/config.py
smart/deprecation.py
smart/mesh.py
smart/model.py
smart/model_assembly.py
smart/solvers.py
smart/units.py
smart/utils.py
smart_cell-0.0.1.dist-info/LICENSE
smart_cell-0.0.1.dist-info/METADATA
smart_cell-0.0.1.dist-info/WHEEL
smart_cell-0.0.1.dist-info/top_level.txt
smart_cell-0.0.1.dist-info/RECORD
