Metadata-Version: 2.1
Name: smart-cell
Version: 0.0.1
Summary: SMART (Spatial Modeling Algorithms for Reaction and Transport) is a tool for spatially modeling cell signaling networks
Author-email: Emmet Francis <emmet.a.francis@gmail.com>
License: GNU LESSER GENERAL PUBLIC LICENSE
Project-URL: homepage, https://rangamanilabucsd.github.io/stubs
Project-URL: repository, https://github.com/RangamaniLabUCSD/stubs
License-File: LICENSE
Requires-Dist: matplotlib
Requires-Dist: numpy (>=1.16.0)
Requires-Dist: pandas
Requires-Dist: Pint
Requires-Dist: scipy (>=1.1.0)
Requires-Dist: sympy
Requires-Dist: dataclasses
Requires-Dist: cached-property
Requires-Dist: tabulate
Requires-Dist: termcolor
Requires-Dist: termplotlib
Requires-Dist: meshio
Requires-Dist: gmsh
Provides-Extra: all
Requires-Dist: smart[test] ; extra == 'all'
Requires-Dist: smart[docs] ; extra == 'all'
Requires-Dist: smart[dev] ; extra == 'all'
Provides-Extra: docs
Requires-Dist: jupyter-book ; extra == 'docs'
Requires-Dist: sphinx-autoapi ; extra == 'docs'
Provides-Extra: test
Requires-Dist: pytest ; extra == 'test'
Requires-Dist: pytest-cov ; extra == 'test'
